wrangles/__init__.py
wrangles/auth.py
wrangles/batching.py
wrangles/classify.py
wrangles/compare.py
wrangles/config.py
wrangles/console.py
wrangles/data.py
wrangles/dataframe.py
wrangles/extract.py
wrangles/format.py
wrangles/generate.py
wrangles/lookup.py
wrangles/openai.py
wrangles/recipe.py
wrangles/select.py
wrangles/standardize.py
wrangles/train.py
wrangles/translate.py
wrangles/utils.py
wrangles/connectors/__init__.py
wrangles/connectors/_formatting.py
wrangles/connectors/akeneo.py
wrangles/connectors/ckan.py
wrangles/connectors/concurrent.py
wrangles/connectors/excel.py
wrangles/connectors/file.py
wrangles/connectors/http.py
wrangles/connectors/input.py
wrangles/connectors/jinja.py
wrangles/connectors/matrix.py
wrangles/connectors/memory.py
wrangles/connectors/mongodb.py
wrangles/connectors/mssql.py
wrangles/connectors/mysql.py
wrangles/connectors/notification.py
wrangles/connectors/postgres.py
wrangles/connectors/pricefx.py
wrangles/connectors/recipe.py
wrangles/connectors/s3.py
wrangles/connectors/salesforce.py
wrangles/connectors/sftp.py
wrangles/connectors/sqlite.py
wrangles/connectors/ssh.py
wrangles/connectors/test.py
wrangles/connectors/train.py
wrangles/recipe_wrangles/__init__.py
wrangles/recipe_wrangles/compare.py
wrangles/recipe_wrangles/compute.py
wrangles/recipe_wrangles/convert.py
wrangles/recipe_wrangles/create.py
wrangles/recipe_wrangles/extract.py
wrangles/recipe_wrangles/format.py
wrangles/recipe_wrangles/generate.py
wrangles/recipe_wrangles/main.py
wrangles/recipe_wrangles/merge.py
wrangles/recipe_wrangles/pandas.py
wrangles/recipe_wrangles/select.py
wrangles/recipe_wrangles/split.py
wrangles-1.16.0.dist-info/METADATA
wrangles-1.16.0.dist-info/WHEEL
wrangles-1.16.0.dist-info/entry_points.txt
wrangles-1.16.0.dist-info/top_level.txt
wrangles-1.16.0.dist-info/RECORD
