Metadata-Version: 2.4
Name: wrangles
Version: 1.16.0
Summary: Wrangle your data into shape with AI
Home-page: https://github.com/wrangleworks/WranglesPy
Author: WrangleWorks
Author-email: chris@wrangleworks.com
License: Apache License 2.0
Project-URL: Bug Tracker, https://github.com/wrangleworks/WranglesPy/issues
Project-URL: Documentation, https://wrangles.io/python
Project-URL: Source Code, https://github.com/wrangleworks/WranglesPy
Keywords: data,wrangling
Classifier: Programming Language :: Python :: 3
Classifier: License :: OSI Approved :: Apache Software License
Classifier: Operating System :: OS Independent
Requires-Dist: requests
Requires-Dist: pyyaml
Requires-Dist: numpy
Requires-Dist: pandas<3.0,>=2.0
Requires-Dist: openpyxl>=3.1.0
Requires-Dist: sqlalchemy<3.0,>=2.0
Requires-Dist: pymssql>=2.3.3
Requires-Dist: psycopg2-binary>=2.9.10
Requires-Dist: pymysql
Requires-Dist: fabric==3.1.0
Requires-Dist: apprise
Requires-Dist: lorem
Requires-Dist: pymongo[srv]
Requires-Dist: simple-salesforce
Requires-Dist: numexpr
Requires-Dist: boto3
Requires-Dist: jinja2
Requires-Dist: polars==1.33.0
Requires-Dist: xlsxwriter
Requires-Dist: pydantic
Dynamic: author
Dynamic: author-email
Dynamic: classifier
Dynamic: description
Dynamic: description-content-type
Dynamic: home-page
Dynamic: keywords
Dynamic: license
Dynamic: project-url
Dynamic: requires-dist
Dynamic: summary
